slowblood/__init__.py
slowblood/lib_dataset.py
slowblood/lib_llm_inference.py
slowblood/lib_model.py
slowblood/lib_pdf.py
slowblood/lib_prompts.py
slowblood/lib_runpod.py
slowblood/lib_settings.py
slowblood/lib_tokenizer.py
slowblood/lib_toolkit.py
slowblood-0.1.1.dist-info/METADATA
slowblood-0.1.1.dist-info/WHEEL
slowblood-0.1.1.dist-info/top_level.txt
slowblood-0.1.1.dist-info/RECORD
