Metadata-Version: 2.1
Name: slowblood
Version: 0.1.1
Summary: Tools for ML/LLM
Home-page: https://github.com/kyledinh/slowblood
Author: Kyle Dinh
Author-email: kyledinh@gmail.com
Project-URL: Bug Tracker, https://github.com/kyledinh/slowblood/issues
Classifier: Programming Language :: Python :: 3
Classifier: License :: OSI Approved :: MIT License
Classifier: Operating System :: OS Independent
Requires-Python: >=3.10
Requires-Dist: bitsandbytes
Requires-Dist: datasets
Requires-Dist: huggingface-hub
Requires-Dist: langchain
Requires-Dist: peft
Requires-Dist: pypandoc
Requires-Dist: pypdfium2
Requires-Dist: pytesseract
Requires-Dist: runpod
Requires-Dist: text-generation
Requires-Dist: torch
